LICENSE
MANIFEST.in
README.md
setup.py
tap_covid_19/__init__.py
tap_covid_19/client.py
tap_covid_19/discover.py
tap_covid_19/schema.py
tap_covid_19/streams.py
tap_covid_19/sync.py
tap_covid_19/transform.py
tap_covid_19.egg-info/PKG-INFO
tap_covid_19.egg-info/SOURCES.txt
tap_covid_19.egg-info/dependency_links.txt
tap_covid_19.egg-info/entry_points.txt
tap_covid_19.egg-info/requires.txt
tap_covid_19.egg-info/top_level.txt
tap_covid_19/schemas/c19_trk_us_daily.json
tap_covid_19/schemas/c19_trk_us_population_counties.json
tap_covid_19/schemas/c19_trk_us_population_states.json
tap_covid_19/schemas/c19_trk_us_population_states_age_groups.json
tap_covid_19/schemas/c19_trk_us_states_acs_health_insurance.json
tap_covid_19/schemas/c19_trk_us_states_current.json
tap_covid_19/schemas/c19_trk_us_states_daily.json
tap_covid_19/schemas/c19_trk_us_states_info.json
tap_covid_19/schemas/c19_trk_us_states_kff_hospital_beds.json
tap_covid_19/schemas/eu_daily.json
tap_covid_19/schemas/eu_ecdc_daily.json
tap_covid_19/schemas/italy_national_daily.json
tap_covid_19/schemas/italy_provincial_daily.json
tap_covid_19/schemas/italy_regional_daily.json
tap_covid_19/schemas/jh_csse_daily.json
tap_covid_19/schemas/neherlab_case_counts.json
tap_covid_19/schemas/neherlab_country_codes.json
tap_covid_19/schemas/neherlab_icu_capacity.json
tap_covid_19/schemas/neherlab_population.json
tap_covid_19/schemas/nytimes_us_counties.json
tap_covid_19/schemas/nytimes_us_states.json