Metadata-Version: 1.1
Name: tap-covid-19
Version: 0.0.8
Summary: Singer.io tap for extracting COVID-19 CSV data files with the GitHub API
Home-page: UNKNOWN
Author: jeff.huth@bytecode.io
Author-email: UNKNOWN
License: UNKNOWN
Platform: UNKNOWN
Classifier: Programming Language :: Python :: 3 :: Only
